models/__init.py
models/recommendation.py
recommender/__init__.py
recommender/data_manager.py
recommender/recommender_system.py
literaryuniverse_recommender-0.1.4.dist-info/METADATA
literaryuniverse_recommender-0.1.4.dist-info/WHEEL
literaryuniverse_recommender-0.1.4.dist-info/top_level.txt
literaryuniverse_recommender-0.1.4.dist-info/RECORD
