Metadata-Version: 2.4
Name: literaryuniverse-recommender
Version: 0.1.4
Summary: Story Recommender System based on LightFM
Author-email: Adam Mitrenga <edemsikk@gmail.com>
Requires-Python: >=3.12
Requires-Dist: lightfm
Requires-Dist: pandas==2.2.3
Requires-Dist: pydantic==2.11.4
Provides-Extra: dev
Requires-Dist: pytest==8.3.5; extra == "dev"
Requires-Dist: pytest-cov==6.1.1; extra == "dev"
Requires-Dist: ruff>=0.11.8; extra == "dev"
